Metadata-Version: 2.4
Name: iflow-mcp_stefanoamorelli_codemagic-mcp
Version: 0.1.0
Summary: Simple MCP server for Codemagic CI/CD
Author-email: Stefano Amorelli <stefano@amorelli.tech>
License: MIT License
Project-URL: Homepage, https://github.com/stefanoamorelli/codemagic-mcp
Project-URL: Bug Tracker, https://github.com/stefanoamorelli/codemagic-mcp/issues
Classifier: Programming Language :: Python :: 3
Classifier: License :: OSI Approved :: MIT License
Classifier: Operating System :: OS Independent
Requires-Python: >=3.10
License-File: LICENSE
Requires-Dist: mcp[cli]>=1.6.0
Requires-Dist: requests
Dynamic: license-file
